[{"username":"u","password":"pap","score":20,"avatarNumber":1,"time":100000},
  {"username":"uu","password":"p444M%33","score":20,"avatarNumber":0,"time":100000},
  {"username":"q","password":"qW@12345","score":18,"avatarNumber":2,"time":100000},
  {"username":"walterBlack","password":"p","score":18,"avatarNumber":0,"time":0},
  {"username":"HanAccompanied","password":"p","score":17,"avatarNumber":0,"time":0},
  {"username":"floridaman","password":"p","score":17,"avatarNumber":2,"time":0},
  {"username":"jesusWaterWalker","password":"p","score":16,"avatarNumber":2,"time":0},
  {"username":"masterPloKoon","password":"p","score":16,"avatarNumber":1,"time":0},
  {"username":"anakinGroundWalker","password":"p","score":15,"avatarNumber":0,"time":0},
  {"username":"bobaFat","password":"p","score":15,"avatarNumber":0,"time":0}]